discopy/__init__.py
discopy/autonomisation.gif
discopy/balanced.py
discopy/braided.py
discopy/cat.py
discopy/closed.py
discopy/compact.py
discopy/config.py
discopy/feedback.py
discopy/frobenius.py
discopy/hypergraph.py
discopy/interaction.py
discopy/markov.py
discopy/matrix.py
discopy/messages.py
discopy/monoidal.py
discopy/pivotal.py
discopy/ribbon.py
discopy/rigid.py
discopy/snake-removal.gif
discopy/stream.py
discopy/symmetric.py
discopy/tensor.py
discopy/traced.py
discopy/utils.py
discopy/version.py
discopy/drawing/__init__.py
discopy/drawing/backend.py
discopy/drawing/drawing.py
discopy/grammar/__init__.py
discopy/grammar/categorial.py
discopy/grammar/cfg.py
discopy/grammar/dependency.py
discopy/grammar/pregroup.py
discopy/grammar/thue.py
discopy/python/__init__.py
discopy/python/additive.py
discopy/python/finset.py
discopy/python/function.py
discopy/python/multiplicative.py
discopy/quantum/__init__.py
discopy/quantum/ansatze.py
discopy/quantum/channel.py
discopy/quantum/circuit.py
discopy/quantum/gates.py
discopy/quantum/pennylane.py
discopy/quantum/tk.py
discopy/quantum/zx.py
discopy-1.2.2.dist-info/licenses/LICENSE
discopy-1.2.2.dist-info/METADATA
discopy-1.2.2.dist-info/WHEEL
discopy-1.2.2.dist-info/top_level.txt
discopy-1.2.2.dist-info/RECORD
