Metadata-Version: 2.4
Name: discopy
Version: 1.2.2
Summary: The Python toolkit for computing with string diagrams.
Author: DisCoPy
Author-email: contact@discopy.org
License: BSD 3-Clause License
Project-URL: Homepage, https://discopy.org
Project-URL: Documentation, https://docs.discopy.org
Project-URL: Repository, https://github.com/discopy/discopy
Project-URL: Issue-Tracker, https://github.com/discopy/discopy/issues
Project-URL: Download, https://pypi.org/project/discopy
Keywords: category theory,string diagrams,natural language processing,quantum computing
Classifier: Development Status :: 5 - Production/Stable
Classifier: Environment :: Console
Classifier: Intended Audience :: Developers
Classifier: Intended Audience :: Science/Research
Classifier: Operating System :: OS Independent
Classifier: Programming Language :: Python :: 3.10
Classifier: Programming Language :: Python :: 3.11
Classifier: Programming Language :: Python :: 3.12
Classifier: Topic :: Scientific/Engineering
Requires-Python: >=3.10
License-File: LICENSE
Requires-Dist: numpy>=1.18.1
Requires-Dist: networkx>=2.4
Requires-Dist: matplotlib>=3.1.2
Requires-Dist: pillow>=6.2.1
Provides-Extra: test
Requires-Dist: pytest; extra == "test"
Requires-Dist: coverage; extra == "test"
Requires-Dist: pyproject-flake8; extra == "test"
Requires-Dist: pytket; extra == "test"
Requires-Dist: pyzx<0.8,>=0.7.3; extra == "test"
Requires-Dist: sympy>=1.13; extra == "test"
Requires-Dist: tensornetwork; extra == "test"
Requires-Dist: jax<=0.4.28; extra == "test"
Requires-Dist: jaxlib<=0.4.28; extra == "test"
Requires-Dist: torch; extra == "test"
Requires-Dist: pennylane==0.34.0; extra == "test"
Requires-Dist: autoray<0.8; extra == "test"
Requires-Dist: pennylane-qiskit; extra == "test"
Requires-Dist: pennylane-honeywell; extra == "test"
Requires-Dist: qiskit<0.46; extra == "test"
Requires-Dist: qiskit-aer; extra == "test"
Requires-Dist: lxml; extra == "test"
Requires-Dist: nltk; extra == "test"
Requires-Dist: pylint; extra == "test"
Requires-Dist: nbmake; extra == "test"
Requires-Dist: quimb; extra == "test"
Provides-Extra: docs
Requires-Dist: sphinx==7.2.*; extra == "docs"
Requires-Dist: sphinx-book-theme==1.1.*; extra == "docs"
Requires-Dist: myst-parser==2.0.*; extra == "docs"
Requires-Dist: nbsphinx==0.9.*; extra == "docs"
Requires-Dist: ipykernel==6.23.*; extra == "docs"
Requires-Dist: sphinxcontrib-youtube==1.4.*; extra == "docs"
Requires-Dist: jinja2==3.1.*; extra == "docs"
Requires-Dist: sphinxcontrib-bibtex==2.5.*; extra == "docs"
Requires-Dist: IPython; extra == "docs"
Dynamic: license-file
